[
    {
        "syriac": "\u0721\u071a\u0715\u071d\u0722\u0710",
        "western": "\u0721\u071a\u0730\u0715\u071d\u0733\u0722\u0733\u0710",
        "number": "singular",
        "gender": "masculine",
        "lexeme": {
            "id": 12039,
            "uri": "https://sedra.bethmardutho.org/api/lexeme/12039.json"
        },
        "stem": "\u0721\u071a\u0715\u071d\u0722\u0710",
        "isLexicalForm": "true",
        "isEnclitic": "false",
        "hasSeyame": "false",
        "isTheoretical": "false",
        "glosses": {
            "eng": [
                "gladdening, giver of joy."
            ]
        },
        "word": {
            "id": 32525,
            "uri": "https://sedra.bethmardutho.org/api/word/32525.json"
        }
    }
]