[
    {
        "syriac": "\u0728\u0721\u072a\u0710",
        "western": "\u0728\u0721\u0733\u072a\u0733\u0710",
        "number": "singular",
        "gender": "masculine",
        "lexeme": {
            "id": 7890,
            "uri": "https://sedra.bethmardutho.org/api/lexeme/7890.json"
        },
        "stem": "\u0728\u0721\u072a\u0710",
        "isLexicalForm": "true",
        "isEnclitic": "false",
        "hasSeyame": "false",
        "isTheoretical": "false",
        "glosses": {
            "ara": [
                "\u0627\u062d\u062a\u0628\u0627\u0633 \u0627\u0644\u0628\u0648\u0644"
            ],
            "eng": [
                ", <span class=\"selectableFont\">\u0728\u0721\u0733\u072a\u072c\u0733\u0710</span> retention of urine.",
                "strangury; stone in the bladder"
            ],
            "fre": [
                "r\u00e9tention d&#39;urine"
            ]
        },
        "word": {
            "id": 34036,
            "uri": "https://sedra.bethmardutho.org/api/word/34036.json"
        }
    }
]