[
    {
        "syriac": "\u0722\u0715\u0722\u0715",
        "western": "\u0722\u0715\u0722\u0715",
        "tense": "perfect",
        "number": "singular",
        "person": "third",
        "gender": "masculine",
        "lexeme": {
            "id": 15040,
            "uri": "https://sedra.bethmardutho.org/api/lexeme/15040.json"
        },
        "stem": "\u0722\u0715\u0722\u0715",
        "category": "verb",
        "isLexicalForm": "true",
        "isEnclitic": "false",
        "hasSeyame": "false",
        "isTheoretical": "true",
        "glosses": {
            "eng": [
                "to be shaken, tossed.",
                "IVp <span class=\"selectableFont\">\u0710\u0736\u072c\u0722\u0730\u0715\u0722\u0730\u0715</span> to shake"
            ]
        },
        "word": {
            "id": 39836,
            "uri": "https://sedra.bethmardutho.org/api/word/39836.json"
        }
    }
]