[
    {
        "syriac": "\u0721\u0725\u071d\u0710",
        "western": "\u0721\u0730\u0725\u071d\u0733\u0710",
        "lexeme": {
            "id": 13498,
            "uri": "https://sedra.bethmardutho.org/api/lexeme/13498.json"
        },
        "stem": "\u0721\u0725\u071d\u0710",
        "isLexicalForm": "false",
        "isEnclitic": "false",
        "hasSeyame": "false",
        "isTheoretical": "false",
        "glosses": {
            "eng": [
                "bowels, viscera, intestines",
                "bowels, intestines.",
                "abdomen",
                "bowels"
            ]
        },
        "word": {
            "id": 43427,
            "uri": "https://sedra.bethmardutho.org/api/word/43427.json"
        }
    }
]