[
    {
        "syriac": "\u0729\u0718\u0722\u071d\u0710",
        "western": "\u0729\u0718\u073d\u0722\u073a\u071d\u0733\u0710",
        "lexeme": {
            "id": 18398,
            "uri": "https://sedra.bethmardutho.org/api/lexeme/18398.json"
        },
        "stem": "\u0729\u0718\u0722\u071d\u0710",
        "isLexicalForm": "true",
        "isEnclitic": "false",
        "hasSeyame": "false",
        "isTheoretical": "false",
        "glosses": {
            "eng": [
                "ashes"
            ]
        },
        "word": {
            "id": 44772,
            "uri": "https://sedra.bethmardutho.org/api/word/44772.json"
        }
    }
]