[
    {
        "syriac": "\u072a\u0712 \u0722\u0726\u072b\u0710",
        "western": "\u072a\u0730\u0712 \u0722\u0730\u0726\u072b\u0733\u0710",
        "lexeme": {
            "id": 20189,
            "uri": "https://sedra.bethmardutho.org/api/lexeme/20189.json"
        },
        "stem": "\u072a\u0712 \u0722\u0726\u072b\u0710",
        "isLexicalForm": "true",
        "isEnclitic": "false",
        "hasSeyame": "false",
        "isTheoretical": "false",
        "glosses": {
            "eng": [
                "magnanimous"
            ]
        },
        "word": {
            "id": 46563,
            "uri": "https://sedra.bethmardutho.org/api/word/46563.json"
        }
    }
]