[
    {
        "syriac": "\u071d\u0718\u0715\u071d\u0710",
        "western": "\u071d\u0718\u073d\u0715\u0733\u071d\u0733\u0710",
        "lexeme": {
            "id": 20421,
            "uri": "https://sedra.bethmardutho.org/api/lexeme/20421.json"
        },
        "stem": "\u071d\u0718\u0715\u071d\u0710",
        "category": "adjective",
        "isLexicalForm": "true",
        "isEnclitic": "false",
        "hasSeyame": "false",
        "isTheoretical": "false",
        "glosses": {
            "eng": [
                "Jewish, Judaic"
            ]
        },
        "word": {
            "id": 46795,
            "uri": "https://sedra.bethmardutho.org/api/word/46795.json"
        }
    }
]