[
    {
        "syriac": "\u0726\u0720\u0713",
        "western": "\u0726\u0730\u0720\u0736\u0713",
        "lexeme": {
            "id": 35157,
            "uri": "https://sedra.bethmardutho.org/api/lexeme/35157.json"
        },
        "stem": "\u0726\u0720\u0713",
        "category": "verb",
        "isLexicalForm": "true",
        "isEnclitic": "false",
        "hasSeyame": "false",
        "isTheoretical": "false",
        "glosses": {
            "eng": [
                "to distribute, to divide up"
            ]
        },
        "word": {
            "id": 61512,
            "uri": "https://sedra.bethmardutho.org/api/word/61512.json"
        }
    }
]