[
    {
        "syriac": "\u0720\u0710 \u0721\u072c\u0721\u0720\u0720",
        "western": "\u0720\u0733\u0710 \u0721\u0736\u072c\u0721\u0730\u0720\u0730\u0720",
        "lexeme": {
            "id": 35756,
            "uri": "https://sedra.bethmardutho.org/api/lexeme/35756.json"
        },
        "stem": "\u0720\u0710 \u0721\u072c\u0721\u0720\u0720",
        "isLexicalForm": "true",
        "isEnclitic": "false",
        "hasSeyame": "false",
        "isTheoretical": "false",
        "glosses": {
            "lat": [
                "ineffabilis"
            ]
        },
        "word": {
            "id": 62111,
            "uri": "https://sedra.bethmardutho.org/api/word/62111.json"
        }
    }
]