[
    {
        "syriac": "\u071a\u0712\u0720\u0712\u0720\u0710",
        "western": "\u071a\u0712\u0736\u0720\u0712\u0720\u0733\u0710",
        "lexeme": {
            "id": 36813,
            "uri": "https://sedra.bethmardutho.org/api/lexeme/36813.json"
        },
        "stem": "\u071a\u0712\u0720\u0712\u0720\u0710",
        "isLexicalForm": "true",
        "isEnclitic": "false",
        "hasSeyame": "false",
        "isTheoretical": "false",
        "glosses": {
            "lat": [
                "planta claviculos agens"
            ]
        },
        "word": {
            "id": 63168,
            "uri": "https://sedra.bethmardutho.org/api/word/63168.json"
        }
    }
]