[
    {
        "syriac": "\u0729\u0718\u072a\u0722\u0720\u071d\u0710",
        "western": "\u0729\u0733\u0718\u072a\u0722\u073a\u0720\u073a\u071d\u0736\u0710",
        "lexeme": {
            "id": 2785,
            "uri": "https://sedra.bethmardutho.org/api/lexeme/2785.json"
        },
        "stem": "\u0729\u0718\u072a\u0722\u071d\u0720\u071d\u0718\u0723",
        "category": "proper noun",
        "isLexicalForm": "false",
        "isEnclitic": "false",
        "hasSeyame": "false",
        "isTheoretical": "false",
        "glosses": {
            "eng": [
                "Cornelius"
            ]
        },
        "word": {
            "id": 18172,
            "uri": "https://sedra.bethmardutho.org/api/word/18172.json"
        }
    }
]