[
    {
        "syriac": "\u0721\u0715\u071d\u0712\u0722\u0710",
        "western": "\u0721\u0715\u0730\u071d\u0712\u0733\u0722\u0733\u0710",
        "number": "singular",
        "gender": "masculine",
        "lexeme": {
            "id": 5155,
            "uri": "https://sedra.bethmardutho.org/api/lexeme/5155.json"
        },
        "stem": "\u0721\u0715\u071d\u0712\u0722\u0710",
        "isLexicalForm": "true",
        "isEnclitic": "false",
        "hasSeyame": "false",
        "isTheoretical": "false",
        "glosses": {
            "eng": [
                "consuming.",
                "causing to waste away"
            ]
        },
        "word": {
            "id": 35312,
            "uri": "https://sedra.bethmardutho.org/api/word/35312.json"
        }
    }
]