[
    {
        "syriac": "\u0712\u0723\u071d\u0710",
        "western": "\u0712\u0723\u0733\u071d\u0733\u0710",
        "eastern": "\u0712\u0723\u0735\u071d\u0710",
        "lexeme": {
            "id": 18582,
            "uri": "https://sedra.bethmardutho.org/api/lexeme/18582.json"
        },
        "stem": "\u0712\u0723\u071d\u0710",
        "category": "adjective",
        "isLexicalForm": "true",
        "isEnclitic": "false",
        "hasSeyame": "false",
        "isTheoretical": "false",
        "glosses": {
            "eng": [
                "vile/vileness"
            ]
        },
        "word": {
            "id": 44956,
            "uri": "https://sedra.bethmardutho.org/api/word/44956.json"
        }
    }
]