[
    {
        "syriac": "\u071a\u071c\u0726",
        "western": "\u071a\u071c\u0730\u0726",
        "lexeme": {
            "id": 19103,
            "uri": "https://sedra.bethmardutho.org/api/lexeme/19103.json"
        },
        "stem": "\u071a\u071c\u0726",
        "category": "verb",
        "isLexicalForm": "true",
        "isEnclitic": "false",
        "hasSeyame": "false",
        "isTheoretical": "false",
        "glosses": {
            "eng": [
                "to be dragged or carried away by force",
                "to take by force",
                "to be seized, pilaged, snatched away",
                "to take by force, do violence, violate; to seize, snatch, catch at"
            ]
        },
        "word": {
            "id": 45477,
            "uri": "https://sedra.bethmardutho.org/api/word/45477.json"
        }
    }
]