[
    {
        "syriac": "\u0710\u071d\u072a\u0718\u0722\u071d",
        "western": "\u0710\u073a\u071d\u072a\u073d\u0718\u0722\u073a\u071d",
        "lexeme": {
            "id": 23275,
            "uri": "https://sedra.bethmardutho.org/api/lexeme/23275.json"
        },
        "stem": "\u0710\u071d\u072a\u0718\u0722\u071d",
        "isLexicalForm": "true",
        "isEnclitic": "false",
        "hasSeyame": "false",
        "isTheoretical": "false",
        "word": {
            "id": 49650,
            "uri": "https://sedra.bethmardutho.org/api/word/49650.json"
        }
    }
]