[
    {
        "syriac": "\u0710\u0723\u0726",
        "western": "\u0710\u0733\u0723\u0733\u0726",
        "eastern": "\u0710\u0735\u0723\u0735\u0726",
        "lexeme": {
            "id": 24097,
            "uri": "https://sedra.bethmardutho.org/api/lexeme/24097.json"
        },
        "stem": "\u0710\u0723\u0726",
        "isLexicalForm": "true",
        "isEnclitic": "false",
        "hasSeyame": "false",
        "isTheoretical": "false",
        "word": {
            "id": 50471,
            "uri": "https://sedra.bethmardutho.org/api/word/50471.json"
        }
    }
]