[
    {
        "syriac": "\u0710\u072c\u072a\u0726\u071d",
        "western": "\u0710\u0736\u072c\u072a\u0726\u073a\u071d",
        "eastern": "\u0710\u072c\u072a\u0726\u071d\u073c",
        "lexeme": {
            "id": 25591,
            "uri": "https://sedra.bethmardutho.org/api/lexeme/25591.json"
        },
        "stem": "\u0710\u072c\u072a\u0726\u071d",
        "isLexicalForm": "true",
        "isEnclitic": "false",
        "hasSeyame": "false",
        "isTheoretical": "false",
        "word": {
            "id": 51965,
            "uri": "https://sedra.bethmardutho.org/api/word/51965.json"
        }
    }
]