[
    {
        "syriac": "\u0712\u0710\u072c",
        "eastern": "\u0712\u073f\u0710\u072c",
        "lexeme": {
            "id": 25719,
            "uri": "https://sedra.bethmardutho.org/api/lexeme/25719.json"
        },
        "stem": "\u0712\u0710\u072c",
        "isLexicalForm": "true",
        "isEnclitic": "false",
        "hasSeyame": "false",
        "isTheoretical": "false",
        "word": {
            "id": 52093,
            "uri": "https://sedra.bethmardutho.org/api/word/52093.json"
        }
    }
]