[
    {
        "syriac": "\u0712\u0715\u0713\u0718\u0722",
        "eastern": "\u0712\u0732\u0715\u0713\u0323\u0718\u0722",
        "lexeme": {
            "id": 9331,
            "uri": "https://sedra.bethmardutho.org/api/lexeme/9331.json"
        },
        "stem": "\u0712\u0715\u0713\u0718\u0722",
        "isLexicalForm": "false",
        "isEnclitic": "false",
        "hasSeyame": "false",
        "isTheoretical": "false",
        "glosses": {
            "ara": [
                "\u0625\u0630\u0627 \u064b, \u0639\u0644\u064a\u0647",
                "\u00a0"
            ],
            "eng": [
                "therefore."
            ],
            "fre": [
                "donc, c\u060cest pourquoi",
                "c\u2019est pourquoi"
            ]
        },
        "word": {
            "id": 52134,
            "uri": "https://sedra.bethmardutho.org/api/word/52134.json"
        }
    }
]