[
    {
        "syriac": "\u0722\u0719\u0715\u0715\u0729",
        "western": "\u0722\u0736\u0719\u0715\u0741\u0730\u0715\u0741\u0730\u0729",
        "tense": "imperfect",
        "kaylo": "ethpa\u02bf\u02bfal",
        "number": "plural",
        "person": "first",
        "gender": "common",
        "lexeme": {
            "id": 848,
            "uri": "https://sedra.bethmardutho.org/api/lexeme/848.json"
        },
        "stem": "\u0719\u0715\u0729",
        "category": "verb",
        "isLexicalForm": "false",
        "isEnclitic": "false",
        "hasSeyame": "false",
        "isTheoretical": "false",
        "glosses": {
            "eng": [
                "justify",
                "Ia <span class=\"selectableFont\">\u0719\u0733\u0715\u0736\u0729</span> it is right, fitting",
                "to assign",
                "IIa to justify, declare righteous",
                "IIp.",
                "to verify",
                "approve",
                "fitting",
                "it is right",
                "to give alms"
            ]
        },
        "word": {
            "id": 5547,
            "uri": "https://sedra.bethmardutho.org/api/word/5547.json"
        }
    }
]