[
    {
        "syriac": "\u0710\u072c\u0722\u071b\u0726",
        "western": "\u0710\u0736\u072c\u0722\u0730\u071b\u0730\u0726",
        "lexeme": {
            "id": 34472,
            "uri": "https://sedra.bethmardutho.org/api/lexeme/34472.json"
        },
        "stem": "\u0710\u072c\u0722\u071b\u0726",
        "category": "verb",
        "isLexicalForm": "true",
        "isEnclitic": "false",
        "hasSeyame": "false",
        "isTheoretical": "false",
        "glosses": {
            "eng": [
                "to fall in drops"
            ]
        },
        "word": {
            "id": 60827,
            "uri": "https://sedra.bethmardutho.org/api/word/60827.json"
        }
    }
]