[
    {
        "syriac": "\u0721\u0718\u0725\u0721\u0725\u0710",
        "western": "\u0721\u0718\u0730\u0725\u0308\u0721\u0733\u0725\u0736\u0710",
        "lexeme": {
            "id": 35782,
            "uri": "https://sedra.bethmardutho.org/api/lexeme/35782.json"
        },
        "stem": "\u0721\u0718\u0725\u0721\u0725\u0710",
        "isLexicalForm": "true",
        "isEnclitic": "false",
        "hasSeyame": "true",
        "isTheoretical": "false",
        "glosses": {
            "lat": [
                "ructationes"
            ]
        },
        "word": {
            "id": 62137,
            "uri": "https://sedra.bethmardutho.org/api/word/62137.json"
        }
    }
]