[
    {
        "syriac": "\u0717\u0718\u0712\u0713\u0710",
        "western": "\u0717\u0730\u0718\u0712\u0733\u0713\u0733\u0710",
        "lexeme": {
            "id": 36677,
            "uri": "https://sedra.bethmardutho.org/api/lexeme/36677.json"
        },
        "stem": "\u0717\u0718\u0712\u0713\u0710",
        "isLexicalForm": "true",
        "isEnclitic": "false",
        "hasSeyame": "false",
        "isTheoretical": "false",
        "glosses": {
            "lat": [
                "odium"
            ]
        },
        "word": {
            "id": 63032,
            "uri": "https://sedra.bethmardutho.org/api/word/63032.json"
        }
    }
]