[
    {
        "syriac": "\u071a\u072b\u071d\u0721\u072c\u0710",
        "western": "\u071a\u072b\u073a\u071d\u0721\u072c\u0733\u0710",
        "lexeme": {
            "id": 37187,
            "uri": "https://sedra.bethmardutho.org/api/lexeme/37187.json"
        },
        "stem": "\u071a\u072b\u071d\u0721\u072c\u0710",
        "isLexicalForm": "true",
        "isEnclitic": "false",
        "hasSeyame": "false",
        "isTheoretical": "false",
        "glosses": {
            "lat": [
                "arcus tectum fulciens"
            ]
        },
        "word": {
            "id": 63542,
            "uri": "https://sedra.bethmardutho.org/api/word/63542.json"
        }
    }
]