[
    {
        "lexeme": {
            "id": 10173,
            "uri": "https://sedra.bethmardutho.org/api/lexeme/10173.json"
        },
        "syriac": "\u0717\u0726\u0718\u071f\u072c\u0722\u0718\u072c\u0710",
        "glosses": {
            "Arabic": [
                "\u062e\u0628\u062b"
            ],
            "French": [
                "malice"
            ],
            "English": [
                "perversity."
            ]
        },
        "etymologies": [],
        "words": [
            {
                "id": 33733,
                "uri": "https://sedra.bethmardutho.org/api/word/33733.json"
            }
        ]
    }
]