[
    {
        "lexeme": {
            "id": 10787,
            "uri": "https://sedra.bethmardutho.org/api/lexeme/10787.json"
        },
        "syriac": "\u0721\u072c\u072c\u071f\u0723\u0722\u0718\u072c\u0710",
        "glosses": {
            "English": [
                "living as a stranger, travelling."
            ]
        },
        "etymologies": [],
        "words": [
            {
                "id": 29835,
                "uri": "https://sedra.bethmardutho.org/api/word/29835.json"
            }
        ]
    }
]