[
    {
        "lexeme": {
            "id": 13281,
            "uri": "https://sedra.bethmardutho.org/api/lexeme/13281.json"
        },
        "syriac": "\u0729\u0718\u0728\u072c\u0710",
        "glosses": {
            "Arabic": [
                "\u062e\u0635\u0644\u0629 \u0645\u0646 \u0634\u0639\u0631"
            ],
            "French": [
                "boucle de cheveux"
            ],
            "English": [
                "curl, lock of hair."
            ]
        },
        "etymologies": [],
        "words": [
            {
                "id": 34648,
                "uri": "https://sedra.bethmardutho.org/api/word/34648.json"
            }
        ]
    }
]