[
    {
        "lexeme": {
            "id": 13357,
            "uri": "https://sedra.bethmardutho.org/api/lexeme/13357.json"
        },
        "syriac": "\u0721\u071f\u0720\u0720\u0722\u0710",
        "glosses": {
            "English": [
                "one who officiates at a wedding ceremony.",
                "crowner"
            ]
        },
        "etymologies": [],
        "words": [
            {
                "id": 35338,
                "uri": "https://sedra.bethmardutho.org/api/word/35338.json"
            }
        ]
    }
]