[
    {
        "lexeme": {
            "id": 13390,
            "uri": "https://sedra.bethmardutho.org/api/lexeme/13390.json"
        },
        "syriac": "\u0722\u0710",
        "glosses": {
            "English": [
                "I beg you, please."
            ],
            "Arabic": [
                "\u0625\u0630\u0627\u064b",
                "\u0647\u0644\u0645, \u0647\u064a\u0627!",
                "\u00a0"
            ],
            "French": [
                "donc",
                "eh bien! allons!",
                "donc\u2026"
            ]
        },
        "etymologies": [],
        "words": [
            {
                "id": 29752,
                "uri": "https://sedra.bethmardutho.org/api/word/29752.json"
            },
            {
                "id": 35429,
                "uri": "https://sedra.bethmardutho.org/api/word/35429.json"
            }
        ]
    }
]