[
    {
        "lexeme": {
            "id": 14399,
            "uri": "https://sedra.bethmardutho.org/api/lexeme/14399.json"
        },
        "syriac": "\u071d\u0725\u072a\u0710",
        "glosses": {
            "Arabic": [
                "\u0639\u0648\u0633\u062c",
                "\u0645\u0635\u064a\u0628\u0629"
            ],
            "French": [
                "broussailles",
                "malheur"
            ],
            "English": [
                "thicket, tangle",
                "briars",
                "sucker",
                "misfortune."
            ]
        },
        "etymologies": [],
        "words": [
            {
                "id": 38233,
                "uri": "https://sedra.bethmardutho.org/api/word/38233.json"
            }
        ]
    }
]