[
    {
        "lexeme": {
            "id": 23939,
            "uri": "https://sedra.bethmardutho.org/api/lexeme/23939.json"
        },
        "syriac": "\u0710\u0722\u072a\u071f\u0718\u0723",
        "glosses": [],
        "etymologies": {
            "Greek": [
                "\u1f04\u03bd\u03b1\u03c1\u03c7\u03bf\u03c2"
            ]
        },
        "words": [
            {
                "id": 50313,
                "uri": "https://sedra.bethmardutho.org/api/word/50313.json"
            }
        ]
    }
]