[
    {
        "lexeme": {
            "id": 29272,
            "uri": "https://sedra.bethmardutho.org/api/lexeme/29272.json"
        },
        "syriac": "\u0710\u071d\u0715\u0718\u0722",
        "glosses": {
            "English": [
                "the nightingale"
            ]
        },
        "etymologies": {
            "Greek": [
                "\u1f00\u03b7\u03b4\u03ce\u03bd"
            ]
        },
        "words": [
            {
                "id": 55646,
                "uri": "https://sedra.bethmardutho.org/api/word/55646.json"
            }
        ],
        "category": "noun"
    }
]