[
    {
        "lexeme": {
            "id": 29581,
            "uri": "https://sedra.bethmardutho.org/api/lexeme/29581.json"
        },
        "syriac": "\u0710\u0726\u071d\u0722\u071d\u071b\u0718\u072a\u0722\u0718",
        "glosses": {
            "English": [
                "aphronitrum"
            ]
        },
        "etymologies": [],
        "words": [
            {
                "id": 55955,
                "uri": "https://sedra.bethmardutho.org/api/word/55955.json"
            }
        ],
        "category": "noun"
    }
]