[
    {
        "lexeme": {
            "id": 30524,
            "uri": "https://sedra.bethmardutho.org/api/lexeme/30524.json"
        },
        "syriac": "\u0717\u0726\u0729\u072c\u0710",
        "glosses": {
            "English": [
                "response, to the contrary"
            ]
        },
        "etymologies": [],
        "words": [
            {
                "id": 56898,
                "uri": "https://sedra.bethmardutho.org/api/word/56898.json"
            }
        ],
        "category": "noun"
    }
]