[
    {
        "lexeme": {
            "id": 30604,
            "uri": "https://sedra.bethmardutho.org/api/lexeme/30604.json"
        },
        "syriac": "\u0719\u071d\u0718\u0725",
        "glosses": {
            "English": [
                "timid"
            ]
        },
        "etymologies": [],
        "words": [
            {
                "id": 56978,
                "uri": "https://sedra.bethmardutho.org/api/word/56978.json"
            }
        ],
        "category": "adjective"
    }
]