[
    {
        "lexeme": {
            "id": 339,
            "uri": "https://sedra.bethmardutho.org/api/lexeme/339.json"
        },
        "syriac": "\u0712\u0715\u072a",
        "glosses": {
            "Arabic": [
                "\u0628\u0630\u0631",
                "\u0628\u062f\u062f",
                "\u00a0"
            ],
            "French": [
                "r\u00e9pandre",
                "disperser",
                "\u00a0"
            ],
            "English": [
                "scatter",
                "disperse",
                "spend",
                "waste",
                "scare away",
                "IIp.",
                "Ia to scatter",
                "IIa to disperse"
            ]
        },
        "etymologies": [],
        "root": {
            "id": 247,
            "uri": "https://sedra.bethmardutho.org/api/root/247.json"
        },
        "words": [
            {
                "id": 23323,
                "uri": "https://sedra.bethmardutho.org/api/word/23323.json"
            },
            {
                "id": 23322,
                "uri": "https://sedra.bethmardutho.org/api/word/23322.json"
            },
            {
                "id": 23321,
                "uri": "https://sedra.bethmardutho.org/api/word/23321.json"
            },
            {
                "id": 23320,
                "uri": "https://sedra.bethmardutho.org/api/word/23320.json"
            },
            {
                "id": 23319,
                "uri": "https://sedra.bethmardutho.org/api/word/23319.json"
            },
            {
                "id": 23318,
                "uri": "https://sedra.bethmardutho.org/api/word/23318.json"
            },
            {
                "id": 23317,
                "uri": "https://sedra.bethmardutho.org/api/word/23317.json"
            },
            {
                "id": 2322,
                "uri": "https://sedra.bethmardutho.org/api/word/2322.json"
            },
            {
                "id": 2330,
                "uri": "https://sedra.bethmardutho.org/api/word/2330.json"
            },
            {
                "id": 2329,
                "uri": "https://sedra.bethmardutho.org/api/word/2329.json"
            },
            {
                "id": 2328,
                "uri": "https://sedra.bethmardutho.org/api/word/2328.json"
            },
            {
                "id": 2327,
                "uri": "https://sedra.bethmardutho.org/api/word/2327.json"
            },
            {
                "id": 2326,
                "uri": "https://sedra.bethmardutho.org/api/word/2326.json"
            },
            {
                "id": 2325,
                "uri": "https://sedra.bethmardutho.org/api/word/2325.json"
            },
            {
                "id": 2324,
                "uri": "https://sedra.bethmardutho.org/api/word/2324.json"
            },
            {
                "id": 2323,
                "uri": "https://sedra.bethmardutho.org/api/word/2323.json"
            },
            {
                "id": 23324,
                "uri": "https://sedra.bethmardutho.org/api/word/23324.json"
            },
            {
                "id": 22765,
                "uri": "https://sedra.bethmardutho.org/api/word/22765.json"
            },
            {
                "id": 2335,
                "uri": "https://sedra.bethmardutho.org/api/word/2335.json"
            },
            {
                "id": 2334,
                "uri": "https://sedra.bethmardutho.org/api/word/2334.json"
            },
            {
                "id": 2333,
                "uri": "https://sedra.bethmardutho.org/api/word/2333.json"
            },
            {
                "id": 2332,
                "uri": "https://sedra.bethmardutho.org/api/word/2332.json"
            },
            {
                "id": 2331,
                "uri": "https://sedra.bethmardutho.org/api/word/2331.json"
            },
            {
                "id": 2321,
                "uri": "https://sedra.bethmardutho.org/api/word/2321.json"
            },
            {
                "id": 2320,
                "uri": "https://sedra.bethmardutho.org/api/word/2320.json"
            },
            {
                "id": 2319,
                "uri": "https://sedra.bethmardutho.org/api/word/2319.json"
            }
        ],
        "category": "verb"
    }
]