[
    {
        "lexeme": {
            "id": 10691,
            "uri": "https://sedra.bethmardutho.org/api/lexeme/10691.json"
        },
        "syriac": "\u072a\u0721\u0719\u0710\u071d\u072c",
        "glosses": {
            "English": [
                "suggestively, hintingly",
                "figuratively",
                "unobtrusively."
            ]
        },
        "etymologies": [],
        "words": [
            {
                "id": 39606,
                "uri": "https://sedra.bethmardutho.org/api/word/39606.json"
            },
            {
                "id": 33612,
                "uri": "https://sedra.bethmardutho.org/api/word/33612.json"
            }
        ]
    }
]