[
    {
        "lexeme": {
            "id": 11244,
            "uri": "https://sedra.bethmardutho.org/api/lexeme/11244.json"
        },
        "syriac": "\u0710\u0723\u0718\u0721\u071b\u0710",
        "glosses": {
            "English": [
                "incorporeal beings."
            ]
        },
        "etymologies": [],
        "words": [
            {
                "id": 50347,
                "uri": "https://sedra.bethmardutho.org/api/word/50347.json"
            },
            {
                "id": 42473,
                "uri": "https://sedra.bethmardutho.org/api/word/42473.json"
            },
            {
                "id": 32508,
                "uri": "https://sedra.bethmardutho.org/api/word/32508.json"
            }
        ]
    }
]