[
    {
        "lexeme": {
            "id": 15677,
            "uri": "https://sedra.bethmardutho.org/api/lexeme/15677.json"
        },
        "syriac": "\u072c\u0720\u071a",
        "glosses": {
            "Arabic": [
                "\u0645\u0632\u0642 (\u0645\u0636)",
                "\u0634\u0642",
                "\u0623\u0628\u0637\u0644",
                "\u00a0"
            ],
            "French": [
                "d\u00e9chirer",
                "fendre",
                "annuler",
                "\u00a0"
            ],
            "English": [
                "to tear, to tear up",
                "IIa to flay, to lacerate.",
                "to be rent apart",
                "Ia to burst asunder",
                "Ip, IIp to be ruptured, to burst open"
            ]
        },
        "etymologies": [],
        "root": {
            "id": 2971,
            "uri": "https://sedra.bethmardutho.org/api/root/2971.json"
        },
        "words": [
            {
                "id": 41917,
                "uri": "https://sedra.bethmardutho.org/api/word/41917.json"
            },
            {
                "id": 40095,
                "uri": "https://sedra.bethmardutho.org/api/word/40095.json"
            }
        ],
        "category": "verb"
    }
]