[
    {
        "lexeme": {
            "id": 17629,
            "uri": "https://sedra.bethmardutho.org/api/lexeme/17629.json"
        },
        "syriac": "\u0723\u072a\u071b\u0718\u0722\u0718\u0722\u0710",
        "glosses": {
            "English": [
                "tiny line, mark"
            ]
        },
        "etymologies": [],
        "words": [
            {
                "id": 44003,
                "uri": "https://sedra.bethmardutho.org/api/word/44003.json"
            }
        ]
    }
]