[
    {
        "lexeme": {
            "id": 17672,
            "uri": "https://sedra.bethmardutho.org/api/lexeme/17672.json"
        },
        "syriac": "\u0725\u0712\u0715 \u0726\u0718\u0722\u071d\u0710",
        "glosses": {
            "English": [
                "to reply"
            ]
        },
        "etymologies": [],
        "words": [
            {
                "id": 44046,
                "uri": "https://sedra.bethmardutho.org/api/word/44046.json"
            }
        ]
    }
]