[
    {
        "lexeme": {
            "id": 17895,
            "uri": "https://sedra.bethmardutho.org/api/lexeme/17895.json"
        },
        "syriac": "\u0726\u0718\u0715\u072a\u0710",
        "glosses": {
            "English": [
                "vulture; lizard; balcony"
            ]
        },
        "etymologies": [],
        "words": [
            {
                "id": 44269,
                "uri": "https://sedra.bethmardutho.org/api/word/44269.json"
            }
        ]
    }
]