[
    {
        "lexeme": {
            "id": 18233,
            "uri": "https://sedra.bethmardutho.org/api/lexeme/18233.json"
        },
        "syriac": "\u0726\u072a\u0728\u0718\u0726\u071d\u0710",
        "glosses": {
            "English": [
                "of person, personal, personifying"
            ]
        },
        "etymologies": [],
        "words": [
            {
                "id": 44607,
                "uri": "https://sedra.bethmardutho.org/api/word/44607.json"
            }
        ]
    }
]