[
    {
        "lexeme": {
            "id": 18867,
            "uri": "https://sedra.bethmardutho.org/api/lexeme/18867.json"
        },
        "syriac": "\u0715\u0710\u0722",
        "glosses": {
            "English": [
                "lord (honorific title)"
            ]
        },
        "etymologies": {
            "Spanish": [
                "don (from Spanish)"
            ]
        },
        "words": [
            {
                "id": 45241,
                "uri": "https://sedra.bethmardutho.org/api/word/45241.json"
            }
        ],
        "category": "noun"
    }
]