[
    {
        "lexeme": {
            "id": 2094,
            "uri": "https://sedra.bethmardutho.org/api/lexeme/2094.json"
        },
        "syriac": "\u0723\u0718\u0722\u071b\u071d\u071f\u0710",
        "glosses": {
            "English": [
                "Syntyche"
            ]
        },
        "etymologies": [],
        "root": {
            "id": 1250,
            "uri": "https://sedra.bethmardutho.org/api/root/1250.json"
        },
        "words": [
            {
                "id": 13940,
                "uri": "https://sedra.bethmardutho.org/api/word/13940.json"
            }
        ],
        "category": "proper noun"
    }
]