[
    {
        "lexeme": {
            "id": 21747,
            "uri": "https://sedra.bethmardutho.org/api/lexeme/21747.json"
        },
        "syriac": "\u0710\u0718\u071d\u0729\u071b\u0718\u072a\u071d\u0710\u0722\u071d",
        "glosses": {
            "Latin": [
                "Victoriana"
            ],
            "Greek": [
                "\u1f38\u03bf\u03c5\u03ba\u03c4\u03bf\u03c1\u03b9\u03b1\u03bd\u03ae"
            ]
        },
        "etymologies": [],
        "words": [
            {
                "id": 48121,
                "uri": "https://sedra.bethmardutho.org/api/word/48121.json"
            }
        ],
        "category": "proper noun (individual's name; e.g. Ephrem)"
    }
]