[
    {
        "lexeme": {
            "id": 26634,
            "uri": "https://sedra.bethmardutho.org/api/lexeme/26634.json"
        },
        "syriac": "\u0713\u0718\u072a\u0721\u071d\u0715\u0710",
        "glosses": {
            "English": [
                "fore-arm/cubit"
            ]
        },
        "etymologies": [],
        "words": [
            {
                "id": 45164,
                "uri": "https://sedra.bethmardutho.org/api/word/45164.json"
            },
            {
                "id": 53008,
                "uri": "https://sedra.bethmardutho.org/api/word/53008.json"
            }
        ]
    }
]