[
    {
        "lexeme": {
            "id": 30903,
            "uri": "https://sedra.bethmardutho.org/api/lexeme/30903.json"
        },
        "syriac": "\u071f\u0710\u0726\u0710 \u0726\u0718\u072a\u071d\u071b\u071d\u0723",
        "glosses": {
            "English": [
                "pyrites"
            ]
        },
        "etymologies": [],
        "words": [
            {
                "id": 57277,
                "uri": "https://sedra.bethmardutho.org/api/word/57277.json"
            }
        ],
        "category": "noun"
    }
]