[
    {
        "lexeme": {
            "id": 31850,
            "uri": "https://sedra.bethmardutho.org/api/lexeme/31850.json"
        },
        "syriac": "\u0723\u071b\u071d\u072b\u071d\u072a\u0710",
        "glosses": {
            "English": [
                "lines"
            ]
        },
        "etymologies": {
            "Greek": [
                "\u03c3\u03c4\u03b9\u03c7\u03b7\u03c1\u03cc\u03c2"
            ]
        },
        "words": [
            {
                "id": 58224,
                "uri": "https://sedra.bethmardutho.org/api/word/58224.json"
            }
        ],
        "category": "noun"
    }
]