[
    {
        "lexeme": {
            "id": 3210,
            "uri": "https://sedra.bethmardutho.org/api/lexeme/3210.json"
        },
        "syriac": "\u072b\u0720\u071a",
        "glosses": {
            "English": [
                "Sala"
            ]
        },
        "etymologies": [],
        "root": {
            "id": 1872,
            "uri": "https://sedra.bethmardutho.org/api/root/1872.json"
        },
        "words": [
            {
                "id": 21052,
                "uri": "https://sedra.bethmardutho.org/api/word/21052.json"
            }
        ],
        "category": "proper noun"
    }
]