[
    {
        "lexeme": {
            "id": 32282,
            "uri": "https://sedra.bethmardutho.org/api/lexeme/32282.json"
        },
        "syriac": "\u0726\u0710\u0722\u0723\u0718\u0726\u071d\u0718\u0723",
        "glosses": {
            "English": [
                "Pansophius"
            ]
        },
        "etymologies": [],
        "words": [
            {
                "id": 58656,
                "uri": "https://sedra.bethmardutho.org/api/word/58656.json"
            }
        ],
        "category": "proper noun"
    }
]