[
    {
        "lexeme": {
            "id": 32731,
            "uri": "https://sedra.bethmardutho.org/api/lexeme/32731.json"
        },
        "syriac": "\u0728\u0726\u072c \u0719\u071d\u0718\u0710",
        "glosses": {
            "English": [
                "Splenditenens"
            ]
        },
        "etymologies": {
            "Greek": [
                "splenditenens"
            ]
        },
        "words": [
            {
                "id": 59105,
                "uri": "https://sedra.bethmardutho.org/api/word/59105.json"
            }
        ],
        "category": "proper noun"
    }
]