[
    {
        "lexeme": {
            "id": 34345,
            "uri": "https://sedra.bethmardutho.org/api/lexeme/34345.json"
        },
        "syriac": "\u0710\u0721\u0723\u072a",
        "glosses": {
            "English": [
                "to hold in contempt"
            ]
        },
        "etymologies": [],
        "root": {
            "id": 1088,
            "uri": "https://sedra.bethmardutho.org/api/root/1088.json"
        },
        "words": [
            {
                "id": 60700,
                "uri": "https://sedra.bethmardutho.org/api/word/60700.json"
            }
        ],
        "category": "verb"
    }
]