[
    {
        "lexeme": {
            "id": 8043,
            "uri": "https://sedra.bethmardutho.org/api/lexeme/8043.json"
        },
        "syriac": "\u0721\u0726\u0713\u0715\u0722\u0710",
        "glosses": {
            "English": [
                "Gram. point above/below letter."
            ]
        },
        "etymologies": [],
        "words": [
            {
                "id": 39467,
                "uri": "https://sedra.bethmardutho.org/api/word/39467.json"
            }
        ]
    }
]